{"frames":{"WalkingDown_0001":{"frame":{"x":8,"y":4,"w":64,"h":128},"rotated":false,"trimmed":false,"spriteSourceSize":{"x":0,"y":0,"w":64,"h":128},"sourceSize":{"w":64,"h":128}},"WalkingDown_0002":{"frame":{"x":96,"y":4,"w":64,"h":128},"rotated":false,"trimmed":false,"spriteSourceSize":{"x":0,"y":0,"w":64,"h":128},"sourceSize":{"w":64,"h":128}},"WalkingDown_0003":{"frame":{"x":184,"y":4,"w":64,"h":128},"rotated":false,"trimmed":false,"spriteSourceSize":{"x":0,"y":0,"w":64,"h":128},"sourceSize":{"w":64,"h":128}},"WalkingDown_0004":{"frame":{"x":272,"y":4,"w":64,"h":128},"rotated":false,"trimmed":false,"spriteSourceSize":{"x":0,"y":0,"w":64,"h":128},"sourceSize":{"w":64,"h":128}},"WalkingDown_0005":{"frame":{"x":360,"y":4,"w":64,"h":128},"rotated":false,"trimmed":false,"spriteSourceSize":{"x":0,"y":0,"w":64,"h":128},"sourceSize":{"w":64,"h":128}},"WalkingDown_0006":{"frame":{"x":448,"y":4,"w":68,"h":128},"rotated":false,"trimmed":false,"spriteSourceSize":{"x":0,"y":0,"w":68,"h":128},"sourceSize":{"w":68,"h":128}},"WalkingDown_0007":{"frame":{"x":536,"y":4,"w":68,"h":128},"rotated":false,"trimmed":false,"spriteSourceSize":{"x":0,"y":0,"w":68,"h":128},"sourceSize":{"w":68,"h":128}},"WalkingLeft_0005":{"frame":{"x":628,"y":4,"w":56,"h":128},"rotated":false,"trimmed":false,"spriteSourceSize":{"x":0,"y":0,"w":56,"h":128},"sourceSize":{"w":56,"h":128}},"WalkingDown_0008":{"frame":{"x":8,"y":140,"w":68,"h":128},"rotated":false,"trimmed":false,"spriteSourceSize":{"x":0,"y":0,"w":68,"h":128},"sourceSize":{"w":68,"h":128}},"WalkingRight_0001":{"frame":{"x":104,"y":140,"w":56,"h":128},"rotated":false,"trimmed":false,"spriteSourceSize":{"x":0,"y":0,"w":56,"h":128},"sourceSize":{"w":56,"h":128}},"WalkingRight_0002":{"frame":{"x":192,"y":140,"w":56,"h":128},"rotated":false,"trimmed":false,"spriteSourceSize":{"x":0,"y":0,"w":56,"h":128},"sourceSize":{"w":56,"h":128}},"WalkingRight_0005":{"frame":{"x":456,"y":140,"w":56,"h":128},"rotated":false,"trimmed":false,"spriteSourceSize":{"x":0,"y":0,"w":56,"h":128},"sourceSize":{"w":56,"h":128}},"WalkingRight_0006":{"frame":{"x":544,"y":140,"w":56,"h":128},"rotated":false,"trimmed":false,"spriteSourceSize":{"x":0,"y":0,"w":56,"h":128},"sourceSize":{"w":56,"h":128}},"WalkingLeft_0006":{"frame":{"x":628,"y":140,"w":56,"h":128},"rotated":false,"trimmed":false,"spriteSourceSize":{"x":0,"y":0,"w":56,"h":128},"sourceSize":{"w":56,"h":128}},"WalkingRight_0003":{"frame":{"x":280,"y":144,"w":56,"h":124},"rotated":false,"trimmed":false,"spriteSourceSize":{"x":0,"y":0,"w":56,"h":124},"sourceSize":{"w":56,"h":124}},"WalkingRight_0004":{"frame":{"x":368,"y":144,"w":56,"h":124},"rotated":false,"trimmed":false,"spriteSourceSize":{"x":0,"y":0,"w":56,"h":124},"sourceSize":{"w":56,"h":124}},"WalkingUp_0001":{"frame":{"x":192,"y":276,"w":64,"h":128},"rotated":false,"trimmed":false,"spriteSourceSize":{"x":0,"y":0,"w":64,"h":128},"sourceSize":{"w":64,"h":128}},"WalkingUp_0002":{"frame":{"x":280,"y":276,"w":64,"h":128},"rotated":false,"trimmed":false,"spriteSourceSize":{"x":0,"y":0,"w":64,"h":128},"sourceSize":{"w":64,"h":128}},"WalkingUp_0003":{"frame":{"x":368,"y":276,"w":64,"h":128},"rotated":false,"trimmed":false,"spriteSourceSize":{"x":0,"y":0,"w":64,"h":128},"sourceSize":{"w":64,"h":128}},"WalkingUp_0004":{"frame":{"x":456,"y":276,"w":64,"h":128},"rotated":false,"trimmed":false,"spriteSourceSize":{"x":0,"y":0,"w":64,"h":128},"sourceSize":{"w":64,"h":128}},"WalkingUp_0005":{"frame":{"x":544,"y":276,"w":64,"h":128},"rotated":false,"trimmed":false,"spriteSourceSize":{"x":0,"y":0,"w":64,"h":128},"sourceSize":{"w":64,"h":128}},"WalkingRight_0007":{"frame":{"x":16,"y":280,"w":56,"h":124},"rotated":false,"trimmed":false,"spriteSourceSize":{"x":0,"y":0,"w":56,"h":124},"sourceSize":{"w":56,"h":124}},"WalkingRight_0008":{"frame":{"x":104,"y":280,"w":56,"h":124},"rotated":false,"trimmed":false,"spriteSourceSize":{"x":0,"y":0,"w":56,"h":124},"sourceSize":{"w":56,"h":124}},"WalkingLeft_0007":{"frame":{"x":628,"y":280,"w":56,"h":124},"rotated":false,"trimmed":false,"spriteSourceSize":{"x":0,"y":0,"w":56,"h":124},"sourceSize":{"w":56,"h":124}},"WalkingUp_0006":{"frame":{"x":12,"y":412,"w":68,"h":128},"rotated":false,"trimmed":false,"spriteSourceSize":{"x":0,"y":0,"w":68,"h":128},"sourceSize":{"w":68,"h":128}},"WalkingUp_0007":{"frame":{"x":100,"y":412,"w":68,"h":128},"rotated":false,"trimmed":false,"spriteSourceSize":{"x":0,"y":0,"w":68,"h":128},"sourceSize":{"w":68,"h":128}},"WalkingUp_0008":{"frame":{"x":188,"y":412,"w":68,"h":128},"rotated":false,"trimmed":false,"spriteSourceSize":{"x":0,"y":0,"w":68,"h":128},"sourceSize":{"w":68,"h":128}},"WalkingLeft_0001":{"frame":{"x":276,"y":412,"w":56,"h":128},"rotated":false,"trimmed":false,"spriteSourceSize":{"x":0,"y":0,"w":56,"h":128},"sourceSize":{"w":56,"h":128}},"WalkingLeft_0002":{"frame":{"x":364,"y":412,"w":56,"h":128},"rotated":false,"trimmed":false,"spriteSourceSize":{"x":0,"y":0,"w":56,"h":128},"sourceSize":{"w":56,"h":128}},"WalkingLeft_0003":{"frame":{"x":452,"y":416,"w":56,"h":124},"rotated":false,"trimmed":false,"spriteSourceSize":{"x":0,"y":0,"w":56,"h":124},"sourceSize":{"w":56,"h":124}},"WalkingLeft_0004":{"frame":{"x":540,"y":416,"w":56,"h":124},"rotated":false,"trimmed":false,"spriteSourceSize":{"x":0,"y":0,"w":56,"h":124},"sourceSize":{"w":56,"h":124}},"WalkingLeft_0008":{"frame":{"x":628,"y":416,"w":56,"h":124},"rotated":false,"trimmed":false,"spriteSourceSize":{"x":0,"y":0,"w":56,"h":124},"sourceSize":{"w":56,"h":124}}},"meta":{"app":"https://www.leshylabs.com/apps/sstool/","version":"Leshy SpriteSheet Tool v0.8.4","image":"spritesheet.png","size":{"w":704,"h":544},"scale":1}}